setup.cfg
setup.py
sunset/__init__.py
sunset/bin.py
sunset/parser.py
sunset/tool.py
sunset.egg-info/PKG-INFO
sunset.egg-info/SOURCES.txt
sunset.egg-info/dependency_links.txt
sunset.egg-info/entry_points.txt
sunset.egg-info/pbr.json
sunset.egg-info/requires.txt
sunset.egg-info/top_level.txt