Metadata-Version: 1.1
Name: sunset
Version: 0.1.2
Summary: Have you ever added a hack that you told yourself you would remember to get rid of later on but it eventually becomes a permanent fixture of the codebase? With Sunset, simply annotate your code with special comments and the scanner will alert you when time has come to clean up your code!
Home-page: https://github.com/jimmyshen/sunset
Author: Jimmy Shen
Author-email: thejimmyshen@gmail.com
License: MIT
Download-URL: https://github.com/jimmyshen/sunset/tarball/v0.1.2
Platform: UNKNOWN
Classifier: Development Status :: 4 - Beta
Classifier: Topic :: Software Development :: Build Tools
Classifier: Programming Language :: Python :: 2.7
Classifier: License :: OSI Approved :: MIT License
